br_eval/__init__.py
br_eval/cep.py
br_eval/cnpj.py
br_eval/cpf.py
br_eval/phone.py
br_eval/plate.py
br_eval/exceptions/__init__.py
br_eval/exceptions/cep_exceptions.py
br_eval/exceptions/cnpj_exceptions.py
br_eval/exceptions/cpf_exceptions.py
br_eval/exceptions/phone_exceptions.py
br_eval/exceptions/plate_exceptions.py
tests/__init__.py
tests/test_cep.py
tests/test_cnpj.py
tests/test_cpf.py
tests/test_phone.py
tests/test_plate.py
br_eval-1.0.1.dist-info/LICENSE
br_eval-1.0.1.dist-info/METADATA
br_eval-1.0.1.dist-info/WHEEL
br_eval-1.0.1.dist-info/top_level.txt
br_eval-1.0.1.dist-info/RECORD
