Metadata-Version: 2.1
Name: br-eval
Version: 1.0.1
Summary: Library for validation and formatting of Brazilian data
Home-page: https://github.com/silvio-machado/br-eval
Author: Silvio Machado
Author-email: silvio.machado@gmail.com
Classifier: Programming Language :: Python :: 3
Classifier: Operating System :: OS Independent
Classifier: License :: OSI Approved :: MIT License
Requires-Python: >=3.6
License-File: LICENSE
